photoimport/__init__.py
photoimport/__main__.py
photoimport/_version.py
photoimport/command.py
photoimport/folders.py
photoimport/photos.py
photoimport/ui.py
photo_import-0.5.0.dist-info/LICENSE
photo_import-0.5.0.dist-info/METADATA
photo_import-0.5.0.dist-info/WHEEL
photo_import-0.5.0.dist-info/entry_points.txt
photo_import-0.5.0.dist-info/top_level.txt
photo_import-0.5.0.dist-info/RECORD
