Metadata-Version: 2.1
Name: photo-import
Version: 0.5.0
Summary: Application to import photos into a hierarchical structure based on the EXIF data of the photos.
Home-page: https://gitlab.com/eddarmitage/photo-import
Author: Edd Armitage
Author-email: edward.armitage@gmail.com
License: MIT
Platform: UNKNOWN
Classifier: Development Status :: 4 - Beta
Classifier: License :: OSI Approved :: MIT License
Classifier: Environment :: Console
Classifier: Natural Language :: English
Classifier: Operating System :: MacOS :: MacOS X
Classifier: Programming Language :: Python :: 3
Classifier: Programming Language :: Python :: 3.6
Classifier: Programming Language :: Python :: 3.7
Classifier: Programming Language :: Python :: 3.8
Requires-Python: >=3.6
Requires-Dist: exif
Requires-Dist: colorama
Requires-Dist: docopt
